minimal.py
minimal_progress-0.0.1.dist-info/LICENSE.md
minimal_progress-0.0.1.dist-info/METADATA
minimal_progress-0.0.1.dist-info/WHEEL
minimal_progress-0.0.1.dist-info/top_level.txt
minimal_progress-0.0.1.dist-info/RECORD
