Metadata-Version: 2.2
Name: minimal-progress
Version: 0.0.1
Summary: A minimal progress UI.
Author: Eris
Classifier: Programming Language :: Python :: 3
Classifier: Operating System :: OS Independent
Requires-Python: >=3.13
License-File: LICENSE.md
